Metadata-Version: 2.4
Name: llm-wrapper_testing
Version: 1.0.3
Summary: A comprehensive Python wrapper for Large Language Models with database integration and usage tracking
Author-email: Akilan R M <akilan@hibizsolutions.com>
Maintainer-email: Akilan R M <akilan@hibizsolutions.com>
License-Expression: MIT
Keywords: llm,language-model,openai,azure,gpt,ai,machine-learning,database,postgresql,mysql,mongodb,usage-tracking,api-wrapper
Classifier: Development Status :: 4 - Beta
Classifier: Intended Audience :: Developers
Classifier: Operating System :: OS Independent
Classifier: Programming Language :: Python :: 3
Classifier: Programming Language :: Python :: 3.8
Classifier: Programming Language :: Python :: 3.9
Classifier: Programming Language :: Python :: 3.10
Classifier: Programming Language :: Python :: 3.11
Classifier: Programming Language :: Python :: 3.12
Classifier: Topic :: Software Development :: Libraries :: Python Modules
Classifier: Topic :: Scientific/Engineering :: Artificial Intelligence
Classifier: Topic :: Database
Classifier: Topic :: Internet :: WWW/HTTP :: HTTP Servers
Requires-Python: >=3.8
License-File: LICENSE
Requires-Dist: requests>=2.25.0
Requires-Dist: psycopg2-binary>=2.9.0
Requires-Dist: sqlalchemy>=2.0.41
Requires-Dist: tiktoken>=0.4.0
Requires-Dist: python-dotenv>=0.19.0
Requires-Dist: typing-extensions>=4.0.0
Dynamic: license-file
